rapidshot/__init__.py
rapidshot/capture.py
rapidshot/_libs/__init__.py
rapidshot/_libs/d3d11.py
rapidshot/_libs/dxgi.py
rapidshot/_libs/user32.py
rapidshot/core/__init__.py
rapidshot/core/device.py
rapidshot/core/duplicator.py
rapidshot/core/output.py
rapidshot/core/stagesurf.py
rapidshot/processor/__init__.py
rapidshot/processor/base.py
rapidshot/processor/cupy_processor.py
rapidshot/processor/numpy_processor.py
rapidshot/processor/pillow_processor.py
rapidshot/util/__init__.py
rapidshot/util/io.py
rapidshot/util/logging.py
rapidshot/util/timer.py
rapidshot-1.1.0.dist-info/licenses/LICENSE
rapidshot-1.1.0.dist-info/METADATA
rapidshot-1.1.0.dist-info/WHEEL
rapidshot-1.1.0.dist-info/top_level.txt
rapidshot-1.1.0.dist-info/RECORD
