Metadata-Version: 2.4
Name: rapidshot
Version: 1.1.0
Summary: A high-performance screencapture library for Windows using Desktop Duplication API
Home-page: https://github.com/Zaatra/Rapidshot
Author: Rapidshot Contributors
Author-email: RapidShot Contributors <example@example.com>
License: MIT
Project-URL: Homepage, https://github.com/Zaatra/Rapidshot
Project-URL: Bug Reports, https://github.com/Zaatra/Rapidshot/issues
Project-URL: Source, https://github.com/Zaatra/Rapidshot
Project-URL: Documentation, https://github.com/Zaatra/Rapidshot
Keywords: screencapture,desktop-duplication,screen-recorder,windows
Classifier: Development Status :: 4 - Beta
Classifier: Intended Audience :: Developers
Classifier: Programming Language :: Python :: 3
Classifier: Programming Language :: Python :: 3.8
Classifier: Programming Language :: Python :: 3.9
Classifier: Programming Language :: Python :: 3.10
Classifier: Programming Language :: Python :: 3.11
Classifier: License :: OSI Approved :: MIT License
Classifier: Operating System :: Microsoft :: Windows
Classifier: Operating System :: Microsoft :: Windows :: Windows 10
Classifier: Operating System :: Microsoft :: Windows :: Windows 11
Classifier: Topic :: Multimedia :: Graphics
Classifier: Topic :: Multimedia :: Graphics :: Capture
Classifier: Topic :: Multimedia :: Graphics :: Capture :: Screen Capture
Requires-Python: >=3.8
License-File: LICENSE
Requires-Dist: numpy>=1.19.0
Requires-Dist: comtypes>=1.1.0
Provides-Extra: cv2
Requires-Dist: opencv-python>=4.5.0; extra == "cv2"
Provides-Extra: gpu
Requires-Dist: cupy-cuda11x>=11.0.0; extra == "gpu"
Requires-Dist: opencv-python>=4.5.0; extra == "gpu"
Provides-Extra: pil
Requires-Dist: pillow>=8.0.0; extra == "pil"
Provides-Extra: all
Requires-Dist: numpy>=1.19.0; extra == "all"
Requires-Dist: comtypes>=1.1.0; extra == "all"
Requires-Dist: opencv-python>=4.5.0; extra == "all"
Requires-Dist: pillow>=8.0.0; extra == "all"
Provides-Extra: dev
Requires-Dist: black>=22.3.0; extra == "dev"
Requires-Dist: isort>=5.10.1; extra == "dev"
Requires-Dist: mypy>=0.950; extra == "dev"
Requires-Dist: pytest>=7.0.0; extra == "dev"
Requires-Dist: pytest-cov>=3.0.0; extra == "dev"
Requires-Dist: flake8>=4.0.1; extra == "dev"
Requires-Dist: tox>=3.24.5; extra == "dev"
Provides-Extra: docs
Requires-Dist: sphinx>=4.5.0; extra == "docs"
Requires-Dist: sphinx-rtd-theme>=1.0.0; extra == "docs"
Requires-Dist: myst-parser>=0.18.0; extra == "docs"
Dynamic: author
Dynamic: home-page
Dynamic: license-file
Dynamic: requires-python
